py_gfe-1.1.6.data/scripts/seq2gfe
pygfe/__init__.py
pygfe/cypher.py
pygfe/pygfe.py
pygfe/util.py
pygfe/feature_client/__init__.py
pygfe/feature_client/api_client.py
pygfe/feature_client/configuration.py
pygfe/feature_client/rest.py
pygfe/feature_client/apis/__init__.py
pygfe/feature_client/apis/features_api.py
pygfe/feature_client/models/__init__.py
pygfe/feature_client/models/feature.py
pygfe/feature_client/models/feature_request.py
pygfe/feature_client/models/sequence.py
pygfe/models/__init__.py
pygfe/models/base_model_.py
pygfe/models/error.py
pygfe/models/feature.py
pygfe/models/seqdiff.py
pygfe/models/typing.py
py_gfe-1.1.6.dist-info/COPYING
py_gfe-1.1.6.dist-info/LICENSE
py_gfe-1.1.6.dist-info/METADATA
py_gfe-1.1.6.dist-info/WHEEL
py_gfe-1.1.6.dist-info/top_level.txt
py_gfe-1.1.6.dist-info/RECORD
