Metadata-Version: 2.1
Name: py-gfe
Version: 1.1.6
Summary: Python package for converting sequence annotations to gene feature enumerations (GFE).
Home-page: https://github.com/nmdp-bioinformatics/py-gfe
Author: CIBMTR
Author-email: cibmtr-pypi@nmdp.org
License: LGPL 3.0
Keywords: pygfe
Classifier: Development Status :: 2 - Pre-Alpha
Classifier: Intended Audience :: Developers
Classifier: License :: OSI Approved :: GNU Lesser General Public License v3 (LGPLv3)
Classifier: Natural Language :: English
Classifier: Programming Language :: Python :: 3.7
Classifier: Programming Language :: Python :: 3.8
Classifier: Programming Language :: Python :: 3.9
License-File: LICENSE
License-File: COPYING
Requires-Dist: seq-ann ==1.1.0
Requires-Dist: more-itertools ==8.7.0
Requires-Dist: neo4j-driver ==1.7.4
Requires-Dist: py2neo-history ==4.3.0
Requires-Dist: pandas >=1.2.3
